<?xml version="1.0" encoding="utf-8" ?>
<dwsync>
<file name="index.php" server="juliegrimes.com/widget_corp/" local="129685766831687125" remote="129685840200000000" />
<file name="staff.php" server="juliegrimes.com/widget_corp/" local="129675327596651820" remote="129675402000000000" />
<file name="content.php" server="juliegrimes.com/widget_corp/" local="129685763410000000" remote="129685835400000000" />
<file name="new_subject.php" server="juliegrimes.com/widget_corp/" local="129685600299966131" remote="129685672200000000" />
<file name="create_subject.php" server="juliegrimes.com/widget_corp/" local="129685674846423969" remote="129685759200000000" />
<file name="edit_subject.php" server="juliegrimes.com/widget_corp/" local="129685758345913782" remote="129685830000000000" />
<file name="delete_subject.php" server="juliegrimes.com/widget_corp/" local="129685720584253208" remote="129685792200000000" />
<file name="edit_page.php" server="juliegrimes.com/widget_corp/" local="129685760893632115" remote="129685832400000000" />
<file name="page_form.php" server="juliegrimes.com/widget_corp/" local="129685751674012499" remote="129685823400000000" />
<file name="new_page.php" server="juliegrimes.com/widget_corp/" local="129685755479928703" remote="129685827600000000" />
</dwsync>